Metadata-Version: 2.1
Name: timeranges
Version: 0.8.0
Summary: Time ranges.
Home-page: https://github.com/MicaelJarniac/timeranges
Author: Micael Jarniac
Author-email: micael@jarniac.dev
License: MIT
Project-URL: Bug Tracker, https://github.com/MicaelJarniac/timeranges/issues
Platform: UNKNOWN
Classifier: Programming Language :: Python :: 3
Classifier: Programming Language :: Python :: 3 :: Only
Classifier: License :: OSI Approved :: MIT License
Classifier: Operating System :: OS Independent
Requires-Python: >=3.8
License-File: LICENSE
